gffpandas/__init__.py
gffpandas/gffpandas.py
gffpandas-0.1.2.dist-info/METADATA
gffpandas-0.1.2.dist-info/RECORD
gffpandas-0.1.2.dist-info/WHEEL
gffpandas-0.1.2.dist-info/top_level.txt
