Metadata-Version: 2.1
Name: gffpandas
Version: 0.1.2
Summary: GFF annotations in panda data frames
Home-page: https://github.com/konrad/gffpandas
Author: Vivian A. Monzon, Konrad U. Förstner
Author-email: vivian.monzon@stud-mail.uni-wuerzburg.de, konrad@foerstner.org
License: ISC license
Keywords: gffpandas
Platform: UNKNOWN
Classifier: Development Status :: 4 - Beta
Classifier: Intended Audience :: Developers
Classifier: License :: OSI Approved :: ISC License (ISCL)
Classifier: Natural Language :: English
Classifier: Programming Language :: Python :: 3
